{"indexes":[{"v":{"$numberInt":"2"},"key":{"_id":{"$numberInt":"1"}},"name":"_id_"},{"v":{"$numberInt":"2"},"key":{"notificationGeneratedAt":{"$numberInt":"1"}},"name":"notificationGeneratedAt_1","expireAfterSeconds":{"$numberInt":"31536000"}},{"v":{"$numberInt":"2"},"key":{"intersectionID":{"$numberInt":"-1"},"notificationGeneratedAt":{"$numberInt":"-1"}},"name":"intersectionID_-1_notificationGeneratedAt_-1"}],"uuid":"d94be37b4fb74a3598d4dd8a21615735","collectionName":"CmSpatTimeChangeDetailsNotification","type":"collection"}